{"cameraMode":{"drawMode":0,"name":"Shaded","section":"Shading Mode"},"sceneLighting":false,"audioPlay":false,"sceneViewState":{"showFog":true,"showMaterialUpdate":false,"showSkybox":false,"showFlares":true,"showImageEffects":true,"showParticleSystems":true},"in2DMode":false,"pivot":{"x":-0.004302263259887695,"y":3.14302659034729,"z":-0.08426117897033692},"rotation":{"x":0.05736685171723366,"y":0.33333930373191836,"z":-0.02032444253563881,"w":0.9408405423164368},"size":16.764863967895509,"orthographic":false}