{"cameraMode":{"drawMode":0,"name":"Shaded","section":"Shading Mode"},"sceneLighting":true,"audioPlay":false,"sceneViewState":{"showFog":true,"showMaterialUpdate":false,"showSkybox":true,"showFlares":true,"showImageEffects":true,"showParticleSystems":true},"in2DMode":false,"pivot":{"x":42.37982177734375,"y":-0.09320030361413956,"z":-4.026724338531494},"rotation":{"x":-0.17489731311798097,"y":-0.2174776792526245,"z":0.03964419662952423,"w":-0.9594491720199585},"size":3.5597829818725588,"orthographic":false}